anime_downloader/__init__.py
anime_downloader/__version__.py
anime_downloader/animeinfo.py
anime_downloader/cli.py
anime_downloader/config.py
anime_downloader/const.py
anime_downloader/gui.py
anime_downloader/session.py
anime_downloader/util.py
anime_downloader/watch.py
anime_downloader/commands/__init__.py
anime_downloader/commands/config.py
anime_downloader/commands/dl.py
anime_downloader/commands/ezdl.py
anime_downloader/commands/gui.py
anime_downloader/commands/test.py
anime_downloader/commands/watch.py
anime_downloader/downloader/SmartDL.py
anime_downloader/downloader/__init__.py
anime_downloader/downloader/base_downloader.py
anime_downloader/downloader/external_downloader.py
anime_downloader/downloader/http_downloader.py
anime_downloader/extractors/3rdparty.py
anime_downloader/extractors/__init__.py
anime_downloader/extractors/animeonline360.py
anime_downloader/extractors/base_extractor.py
anime_downloader/extractors/clipwatching.py
anime_downloader/extractors/cloud9.py
anime_downloader/extractors/eplay.py
anime_downloader/extractors/fake_extractor.py
anime_downloader/extractors/gcloud.py
anime_downloader/extractors/haloani.py
anime_downloader/extractors/hydrax.py
anime_downloader/extractors/init.py
anime_downloader/extractors/kwik.py
anime_downloader/extractors/mixdrop.py
anime_downloader/extractors/moe.py
anime_downloader/extractors/mp4sh.py
anime_downloader/extractors/mp4upload.py
anime_downloader/extractors/rapidvideo.py
anime_downloader/extractors/sendvid.py
anime_downloader/extractors/sibnet.py
anime_downloader/extractors/streamango.py
anime_downloader/extractors/streamium.py
anime_downloader/extractors/streamtape.py
anime_downloader/extractors/streamx.py
anime_downloader/extractors/trollvid.py
anime_downloader/extractors/uqload.py
anime_downloader/extractors/vidstream.py
anime_downloader/extractors/vudeo.py
anime_downloader/extractors/xstreamcdn.py
anime_downloader/extractors/yify.py
anime_downloader/extractors/yourupload.py
anime_downloader-5.0.9.dist-info/LICENSE
anime_downloader-5.0.9.dist-info/METADATA
anime_downloader-5.0.9.dist-info/WHEEL
anime_downloader-5.0.9.dist-info/entry_points.txt
anime_downloader-5.0.9.dist-info/top_level.txt
anime_downloader-5.0.9.dist-info/RECORD
