Metadata-Version: 2.1
Name: anime-downloader
Version: 5.0.9
Summary: Download your favourite anime
Home-page: https://github.com/vn-ki/anime-downloader
Author: Vishnunarayan K.I.
Author-email: vishnunarayan6105@gmail.com
License: UNKNOWN
Keywords: anime,downloader,9anime,download,kissanime
Platform: UNKNOWN
Requires-Dist: pySmartDL (>=1.3.4)
Requires-Dist: beautifulsoup4 (>=4.6.0)
Requires-Dist: requests (>=2.18.4)
Requires-Dist: Click (>=6.7)
Requires-Dist: fuzzywuzzy (>=0.17.0)
Requires-Dist: coloredlogs (>=10.0)
Requires-Dist: cfscrape (>=2.0.5)
Requires-Dist: requests-cache (>=0.4.13)
Requires-Dist: tabulate (>=0.8.3)
Requires-Dist: pycryptodome (>=3.8.2)
Provides-Extra: dev
Requires-Dist: pytest ; extra == 'dev'
Requires-Dist: httpretty ; extra == 'dev'
Provides-Extra: gui
Requires-Dist: PyQt5 (>=5.15.1) ; extra == 'gui'
Requires-Dist: selenium ; extra == 'gui'
Provides-Extra: selescrape
Requires-Dist: selenium ; extra == 'selescrape'
Provides-Extra: unpacker
Requires-Dist: jsbeautifier (==1.11.0) ; extra == 'unpacker'
